{
  "date": "2026-04-09",
  "buckets": [
    {
      "name": "21EMA",
      "tickers": []
    },
    {
      "name": "4% Bullish",
      "tickers": [
        "CAR",
        "PVH",
        "INTC",
        "CROX",
        "BF-B",
        "RMBS",
        "AMZN",
        "FOXA",
        "STZ",
        "HGV"
      ]
    },
    {
      "name": "Vol Up",
      "tickers": [
        "CAR",
        "INTC",
        "CROX",
        "BF-B",
        "WAB",
        "FOXA",
        "STZ",
        "CVLT"
      ]
    },
    {
      "name": "Momentum 97",
      "tickers": [
        "CAR",
        "PVH",
        "STX",
        "SNDK",
        "GLW",
        "INTC",
        "WDC",
        "TER",
        "LRCX",
        "KLAC",
        "ENTG",
        "AMAT",
        "MU"
      ]
    },
    {
      "name": "97 Club",
      "tickers": []
    },
    {
      "name": "VCS",
      "tickers": []
    },
    {
      "name": "Pocket Pivot",
      "tickers": [
        "CAR",
        "INTC",
        "CROX",
        "BF-B",
        "HOG",
        "TER",
        "FLEX",
        "CRUS",
        "FN",
        "ENS",
        "VLY",
        "WFRD",
        "CAT",
        "ARW",
        "WAB",
        "PNFP",
        "AMZN",
        "AVT",
        "OZK",
        "STZ",
        "CFR",
        "HLT",
        "FLS",
        "NUE",
        "FTV",
        "JBHT",
        "VC",
        "CBSH",
        "PPL",
        "GWW",
        "CMS",
        "NI",
        "TJX",
        "AWK",
        "IPGP",
        "XEL",
        "USFD",
        "WELL",
        "IDCC"
      ]
    },
    {
      "name": "PP Count",
      "tickers": []
    },
    {
      "name": "Weekly 20%+ Gainers",
      "tickers": [
        "CAR",
        "SNDK",
        "INTC",
        "CROX"
      ]
    }
  ]
}