{
  "date": "2026-03-25",
  "buckets": [
    {
      "name": "21EMA",
      "tickers": []
    },
    {
      "name": "4% Bullish",
      "tickers": [
        "HPE",
        "CHWY"
      ]
    },
    {
      "name": "Vol Up",
      "tickers": []
    },
    {
      "name": "Momentum 97",
      "tickers": [
        "DELL",
        "CIEN",
        "OLN",
        "LITE",
        "NXT",
        "GEV",
        "Q",
        "JBL",
        "SLB",
        "AMKR",
        "TTMI",
        "LSCC",
        "MTSI",
        "TER",
        "ALB",
        "GLW"
      ]
    },
    {
      "name": "97 Club",
      "tickers": []
    },
    {
      "name": "VCS",
      "tickers": [
        "MASI",
        "SLAB"
      ]
    },
    {
      "name": "Pocket Pivot",
      "tickers": []
    },
    {
      "name": "PP Count",
      "tickers": []
    },
    {
      "name": "Weekly 20%+ Gainers",
      "tickers": [
        "FN",
        "GLW",
        "FOUR"
      ]
    }
  ]
}