{
  "date": "2026-06-26",
  "buckets": [
    {
      "name": "21EMA",
      "tickers": []
    },
    {
      "name": "4% Bullish",
      "tickers": []
    },
    {
      "name": "Vol Up",
      "tickers": [
        "SYNA"
      ]
    },
    {
      "name": "Momentum 97",
      "tickers": [
        "TECH",
        "AAL",
        "UAL",
        "BAX",
        "BBWI",
        "RVTY"
      ]
    },
    {
      "name": "97 Club",
      "tickers": []
    },
    {
      "name": "VCS",
      "tickers": [
        "TMHC"
      ]
    },
    {
      "name": "Pocket Pivot",
      "tickers": [
        "TECH",
        "SYNA"
      ]
    },
    {
      "name": "PP Count",
      "tickers": []
    },
    {
      "name": "Weekly 20%+ Gainers",
      "tickers": [
        "TECH"
      ]
    }
  ]
}